analysis_usedecorator.py
datapeachcli.py
templates/LICENSE
templates/README.md
templates/__init__.py
templates/requirements.txt
templates/setup.j2
templates/datapeach.egg-info/PKG-INFO
templates/datapeach.egg-info/SOURCES.txt
templates/datapeach.egg-info/dependency_links.txt
templates/datapeach.egg-info/entry_points.txt
templates/datapeach.egg-info/requires.txt
templates/datapeach.egg-info/top_level.txt
templates/src/__init__.py
templates/src/main.py
templates/src/main_async.py
datapeach_cli-1.0.3.dist-info/METADATA
datapeach_cli-1.0.3.dist-info/WHEEL
datapeach_cli-1.0.3.dist-info/entry_points.txt
datapeach_cli-1.0.3.dist-info/top_level.txt
datapeach_cli-1.0.3.dist-info/RECORD
