Metadata-Version: 2.1
Name: datapeach-cli
Version: 1.0.3
Requires-Dist: click
Requires-Dist: jinja2
Requires-Dist: nbformat
Requires-Dist: nbconvert
Requires-Dist: pandas
Requires-Dist: pyyaml
Requires-Dist: ipython
Requires-Dist: requests
Requires-Dist: datapeach-wrapper
